MANIFEST.in
setup.cfg
setup.py
PyImage3D/Image3D.py
PyImage3D/__init__.py
PyImage3D.egg-info/PKG-INFO
PyImage3D.egg-info/SOURCES.txt
PyImage3D.egg-info/dependency_links.txt
PyImage3D.egg-info/top_level.txt
PyImage3D/Image/__init__.py
PyImage3D/Image/color.py
PyImage3D/Image/coordinate.py
PyImage3D/Image/driver.py
PyImage3D/Image/helper.py
PyImage3D/Image/line.py
PyImage3D/Image/matrix.py
PyImage3D/Image/point.py
PyImage3D/Image/renderer.py
PyImage3D/Image/vector.py
PyImage3D/Image/Driver/SVG.py
PyImage3D/Image/Driver/__init__.py
PyImage3D/Image/Matrix/__init__.py
PyImage3D/Image/Matrix/move.py
PyImage3D/Image/Matrix/rotate.py
PyImage3D/Image/Matrix/scale.py
PyImage3D/Image/Paintable/__init__.py
PyImage3D/Image/Paintable/light.py
PyImage3D/Image/Paintable/object.py
PyImage3D/Image/Paintable/polygon.py
PyImage3D/Image/Paintable/Light/__init__.py
PyImage3D/Image/Paintable/Light/ambient.py
PyImage3D/Image/Paintable/Object/__init__.py
PyImage3D/Image/Paintable/Object/zcube.py
PyImage3D/Image/Renderer/__init__.py
PyImage3D/Image/Renderer/perspective.py