Metadata-Version: 1.1
Name: PyImage3D
Version: 0.1.5
Summary: PyImage3D is a Python port of the PHP's Image3D library.
Home-page: https://bitbucket.org/Naltharial/pyimage3d
Author: Primož 'Naltharial' Jeras
Author-email: primoz.jeras@offblast.si
License: UNKNOWN
Download-URL: https://bitbucket.org/Naltharial/pyimage3d/get/0.1.tar.gz
Keywords: 3d,image,render
Platform: UNKNOWN
